easydata/__init__.py
easydata/blocks.py
easydata/data.py
easydata/exceptions.py
easydata/groups.py
easydata/loaders.py
easydata/managers.py
easydata/mixins.py
easydata/models.py
easydata/typing.py
easydata/config/__init__.py
easydata/config/default.py
easydata/config/loader.py
easydata/contrib/__init__.py
easydata/contrib/requests/__init__.py
easydata/contrib/requests/models.py
easydata/contrib/requests/utils.py
easydata/contrib/scrapy/__init__.py
easydata/contrib/scrapy/extensions.py
easydata/contrib/scrapy/models.py
easydata/contrib/scrapy/spiders.py
easydata/contrib/scrapy/utils.py
easydata/parsers/__init__.py
easydata/parsers/base.py
easydata/parsers/choice.py
easydata/parsers/clause.py
easydata/parsers/data.py
easydata/parsers/desc.py
easydata/parsers/dict.py
easydata/parsers/drop.py
easydata/parsers/email.py
easydata/parsers/has.py
easydata/parsers/list.py
easydata/parsers/math.py
easydata/parsers/misc.py
easydata/parsers/number.py
easydata/parsers/price.py
easydata/parsers/text.py
easydata/parsers/time.py
easydata/parsers/url.py
easydata/processors/__init__.py
easydata/processors/base.py
easydata/processors/data.py
easydata/processors/item.py
easydata/queries/__init__.py
easydata/queries/base.py
easydata/queries/clause.py
easydata/queries/jp.py
easydata/queries/key.py
easydata/queries/pq.py
easydata/queries/re.py
easydata/utils/__init__.py
easydata/utils/email.py
easydata/utils/mix.py
easydata/utils/parse.py
easydata/utils/price.py
easydata/utils/pseudo.py
easydata/utils/url.py
easydata/utils/validate.py
tests/contrib/__init__.py
tests/contrib/requests/__init__.py
tests/contrib/requests/test_models.py
tests/contrib/requests/test_utils.py
tests/contrib/scrapy/__init__.py
tests/contrib/scrapy/test_models.py
tests/contrib/scrapy/test_spiders.py
tests/contrib/scrapy/test_utils.py
tests/factory/__init__.py
tests/factory/data_dict.py
tests/factory/data_html.py
tests/factory/data_list.py
tests/factory/data_text.py
tests/factory/models.py
tests/factory/requests.py
easydata-0.3.11.dist-info/LICENSE
easydata-0.3.11.dist-info/METADATA
easydata-0.3.11.dist-info/WHEEL
easydata-0.3.11.dist-info/top_level.txt
easydata-0.3.11.dist-info/RECORD
