Metadata-Version: 2.1
Name: easydata
Version: 0.3.11
Summary: Data transformation and manipulation library
Home-page: https://github.com/sitegroove/easydata
Author: EasyData developers
Author-email: grabnarrok@gmail.com
License: BSD 3-Clause
Project-URL: Bug Reports, https://github.com/sitegroove/easydata/issues
Project-URL: Source, https://github.com/sitegroove/easydata
Project-URL: Documentation, https://easydata.readthedocs.io/en/latest/
Classifier: Development Status :: 2 - Pre-Alpha
Classifier: Intended Audience :: Developers
Classifier: License :: OSI Approved :: BSD License
Classifier: Natural Language :: English
Classifier: Operating System :: OS Independent
Classifier: Programming Language :: Python :: 3
Classifier: Programming Language :: Python :: 3.8
Classifier: Programming Language :: Python :: 3.9
Requires-Python: >=3.8
License-File: LICENSE
Requires-Dist: dateparser
Requires-Dist: easytxt
Requires-Dist: furl
Requires-Dist: ftfy
Requires-Dist: jmespath
Requires-Dist: price-parser
Requires-Dist: pyquery
Requires-Dist: pyyaml
Requires-Dist: xmltodict
